LICENSE
README.md
setup.py
propelauth_flask/__init__.py
propelauth_flask/auth_decorator.py
propelauth_flask/user.py
propelauth_flask.egg-info/PKG-INFO
propelauth_flask.egg-info/SOURCES.txt
propelauth_flask.egg-info/dependency_links.txt
propelauth_flask.egg-info/requires.txt
propelauth_flask.egg-info/top_level.txt