Metadata-Version: 2.1
Name: propelauth-flask
Version: 4.2.8
Summary: A library for managing authentication in Flask
Home-page: https://github.com/propelauth/propelauth-flask
Author: PropelAuth
Author-email: support@propelauth.com
License: MIT
Platform: UNKNOWN
License-File: LICENSE
